raha/__init__.py
raha/baselines.py
raha/benchmark.py
raha/correction.py
raha/dataset.py
raha/detection.py
raha/utilities.py
raha/tools/__init__.py
raha/tools/KATARA/__init__.py
raha/tools/KATARA/katara.py
raha/tools/KATARA/knowledge-base/zipHasCity.rel.txt
raha/tools/dBoost/LICENSE
raha/tools/dBoost/README.md
raha/tools/dBoost/TODO
raha/tools/dBoost/dboost-mimic2.py
raha/tools/dBoost/group-list.md
raha/tools/dBoost/twitter.py
raha/tools/dBoost/datasets/all
raha/tools/dBoost/datasets/invocation.md
raha/tools/dBoost/datasets/urls.txt
raha/tools/dBoost/datasets/synthetic/country_data
raha/tools/dBoost/datasets/synthetic/countrydata.py
raha/tools/dBoost/datasets/synthetic/fizzbuzz.py
raha/tools/dBoost/datasets/synthetic/logins.py
raha/tools/dBoost/datasets/synthetic/utils.py
raha/tools/dBoost/dboost/__init__.py
raha/tools/dBoost/dboost/cli.py
raha/tools/dBoost/dboost/dboost-stdin.py
raha/tools/dBoost/dboost/imported_dboost.py
raha/tools/dBoost/dboost/analyzers/__init__.py
raha/tools/dBoost/dboost/analyzers/cords.py
raha/tools/dBoost/dboost/analyzers/discrete.py
raha/tools/dBoost/dboost/analyzers/statistical.py
raha/tools/dBoost/dboost/analyzers/utils.py
raha/tools/dBoost/dboost/features/__init__.py
raha/tools/dBoost/dboost/features/utils.py
raha/tools/dBoost/dboost/models/__init__.py
raha/tools/dBoost/dboost/models/discrete.py
raha/tools/dBoost/dboost/models/discretepart.py
raha/tools/dBoost/dboost/models/gaussian.py
raha/tools/dBoost/dboost/models/mixture.py
raha/tools/dBoost/dboost/utils/__init__.py
raha/tools/dBoost/dboost/utils/autoconv.py
raha/tools/dBoost/dboost/utils/color.py
raha/tools/dBoost/dboost/utils/db.py
raha/tools/dBoost/dboost/utils/printing.py
raha/tools/dBoost/dboost/utils/read.py
raha/tools/dBoost/dboost/utils/tupleops.py
raha/tools/dBoost/graphics/3d-plots.pdf.py
raha/tools/dBoost/graphics/csail-stats.pdf.py
raha/tools/dBoost/graphics/gaussians-preview.pdf.py
raha/tools/dBoost/graphics/histograms-preview.pdf.py
raha-1.26.dist-info/LICENSE.md
raha-1.26.dist-info/METADATA
raha-1.26.dist-info/WHEEL
raha-1.26.dist-info/top_level.txt
raha-1.26.dist-info/RECORD
