Metadata-Version: 2.1
Name: raha
Version: 1.26
Summary: Raha and Baran: An End-to-End Data Cleaning System
Home-page: https://github.com/bigdama/raha
Download-URL: https://github.com/BigDaMa/raha/archive/v1.26.tar.gz
Author: Mohammad Mahdavi
Author-email: moh.mahdavi.l@gmail.com
License: Apache 2.0
Keywords: Data Cleaning,Machine Learning,Error Detection,Error Correction,Data Repairing
License-File: LICENSE.md
Requires-Dist: numpy
Requires-Dist: pandas
Requires-Dist: scipy
Requires-Dist: scikit-learn
Requires-Dist: matplotlib
Requires-Dist: prettytable
Requires-Dist: mwparserfromhell
Requires-Dist: beautifulsoup4
Requires-Dist: py7zr
